addata/.DS_Store
addata/__init__.py
addata/addata.py
addata/datasets/churn.csv
addata/datasets/new_sales.csv
addata-0.1.0.dist-info/WHEEL
addata-0.1.0.dist-info/METADATA
addata-0.1.0.dist-info/RECORD
